langrun/__init__.py
langrun-23.2.26.dist-info/LICENSE
langrun-23.2.26.dist-info/METADATA
langrun-23.2.26.dist-info/WHEEL
langrun-23.2.26.dist-info/top_level.txt
langrun-23.2.26.dist-info/RECORD
