Metadata-Version: 2.1
Name: langrun
Version: 23.2.26
Summary: a simple package for running seperate languages in python
Home-page: https://replit.com/@-jpg/langrun
Author: zalo_halo
Author-email: aidenkundert060@gmail.com
Classifier: Programming Language :: Python :: 3
Classifier: License :: OSI Approved :: MIT License
Classifier: Operating System :: OS Independent
Requires-Python: >=3.6
License-File: LICENSE
